[
    {
        "degree": 1,
        "params": [
            -0.1639113758,
            0.001443124
        ],
        "aic": -76.5349183884,
        "rsquared": 0.8142296337,
        "mse": 1.2692393481
    },
    {
        "degree": 2,
        "params": [
            -0.2087502357,
            0.0022651115,
            -2.1501e-06
        ],
        "aic": -78.0759061611,
        "rsquared": 0.8303535165,
        "mse": 0.6471868085
    },
    {
        "degree": 3,
        "params": [
            -0.0990730694,
            -0.0015526559,
            2.2958e-05,
            -4.31e-08
        ],
        "aic": -98.6808300123,
        "rsquared": 0.9049784858,
        "mse": 0.4702335623
    },
    {
        "degree": 4,
        "params": [
            -0.0127476209,
            -0.0064171474,
            8.04766e-05,
            -2.705e-07,
            3e-10
        ],
        "aic": -117.3158952728,
        "rsquared": 0.944019742,
        "mse": 0.3678897673
    },
    {
        "degree": 5,
        "params": [
            0.0443683281,
            -0.0114464119,
            0.0001759706,
            -9.318e-07,
            2.2e-09,
            -0.0
        ],
        "aic": -128.7858752132,
        "rsquared": 0.9603688672,
        "mse": 0.2994088902
    },
    {
        "degree": 6,
        "params": [
            -0.0005152822,
            -0.0081228401,
            0.0001033372,
            -2.599e-07,
            -8e-10,
            0.0,
            -0.0
        ],
        "aic": -127.7333086006,
        "rsquared": 0.9592847026,
        "mse": 0.2990708862
    }
]