[
    {
        "degree": 1,
        "params": [
            1.2750063008,
            -0.0022786343
        ],
        "aic": -1.8074403203,
        "rsquared": 0.5847250612,
        "rsquared_adj": 0.5681140636,
        "mse": 1.7951173021
    },
    {
        "degree": 2,
        "params": [
            1.6129993061,
            -0.0084971264,
            1.71112e-05
        ],
        "aic": -53.6187753765,
        "rsquared": 0.9434045612,
        "rsquared_adj": 0.9386882747,
        "mse": 1.4481351692
    },
    {
        "degree": 3,
        "params": [
            1.6341586392,
            -0.0094625804,
            2.45377e-05,
            -1.41e-08
        ],
        "aic": -52.3009018961,
        "rsquared": 0.944816475,
        "rsquared_adj": 0.9376186239,
        "mse": 0.9668683136
    },
    {
        "degree": 4,
        "params": [
            1.6202334706,
            -0.0083143594,
            8.2367e-06,
            6.2e-08,
            -1e-10
        ],
        "aic": -50.7050817085,
        "rsquared": 0.9456363992,
        "rsquared_adj": 0.9357521082,
        "mse": 0.7257805311
    },
    {
        "degree": 5,
        "params": [
            1.6026701163,
            -0.0060464623,
            -4.01799e-05,
            4.311e-07,
            -1.3e-09,
            0.0
        ],
        "aic": -49.1412103052,
        "rsquared": 0.9465074755,
        "rsquared_adj": 0.9337711601,
        "mse": 0.5811592691
    },
    {
        "degree": 6,
        "params": [
            0.0111423621,
            0.1334751136,
            -0.0033840684,
            3.44772e-05,
            -1.686e-07,
            4e-10,
            -0.0
        ],
        "aic": 34.8813209551,
        "rsquared": -0.2016940132,
        "rsquared_adj": -0.4878116354,
        "mse": -0.1238409081
    }
]