[
    {
        "degree": 1,
        "params": [
            0.4646932791,
            0.0003661699
        ],
        "aic": -59.0653562722,
        "rsquared": 0.1461533874,
        "mse": 0.053318343
    },
    {
        "degree": 2,
        "params": [
            0.3005409491,
            0.0031324115,
            -7.5669e-06
        ],
        "aic": -126.8018247316,
        "rsquared": 0.8901979757,
        "mse": 0.1623769448
    },
    {
        "degree": 3,
        "params": [
            0.2482344205,
            0.005094077,
            -2.09646e-05,
            2.37e-08
        ],
        "aic": -149.5434715282,
        "rsquared": 0.9469633348,
        "mse": 0.1151541697
    },
    {
        "degree": 4,
        "params": [
            0.2562139957,
            0.0045891814,
            -1.46495e-05,
            -3.1e-09,
            0.0
        ],
        "aic": -148.2981115598,
        "rsquared": 0.9481275316,
        "mse": 0.0864718052
    },
    {
        "degree": 5,
        "params": [
            0.2391391412,
            0.0062578497,
            -4.80236e-05,
            2.426e-07,
            -7e-10,
            0.0
        ],
        "aic": -149.7158195215,
        "rsquared": 0.9530882886,
        "mse": 0.0695393918
    },
    {
        "degree": 6,
        "params": [
            0.0016521519,
            0.0241816668,
            -0.0004448016,
            4.0327e-06,
            -1.83e-08,
            0.0,
            -0.0
        ],
        "aic": -101.5103530954,
        "rsquared": 0.8063455878,
        "mse": 0.0588327256
    }
]