[
    {
        "degree": 1,
        "params": [
            0.2821955623,
            0.0020033448
        ],
        "aic": -28.237291739,
        "rsquared": 0.6811951485,
        "mse": 0.7836646729
    },
    {
        "degree": 2,
        "params": [
            0.1166650443,
            0.0064124085,
            -1.5595e-05
        ],
        "aic": -97.1595584304,
        "rsquared": 0.9833986383,
        "mse": 0.5656637264
    },
    {
        "degree": 3,
        "params": [
            0.1238698536,
            0.0060154291,
            -1.18758e-05,
            -8.5e-09
        ],
        "aic": -95.9174965459,
        "rsquared": 0.9839147297,
        "mse": 0.3773070593
    },
    {
        "degree": 4,
        "params": [
            0.1448148613,
            0.0041716096,
            1.83027e-05,
            -1.698e-07,
            3e-10
        ],
        "aic": -99.1309284518,
        "rsquared": 0.9870554139,
        "mse": 0.2838835757
    },
    {
        "degree": 5,
        "params": [
            0.1515038776,
            0.0032496077,
            4.35589e-05,
            -4.171e-07,
            1.2e-09,
            -0.0
        ],
        "aic": -97.7348935736,
        "rsquared": 0.9873771026,
        "mse": 0.2271808764
    },
    {
        "degree": 6,
        "params": [
            0.1638454741,
            0.0009285426,
            0.000132577,
            -1.7063e-06,
            9.8e-09,
            -0.0,
            0.0
        ],
        "aic": -100.5315352579,
        "rsquared": 0.9887655417,
        "mse": 0.2275003357
    }
]